WebSearcher/__init__.py
WebSearcher/classifiers/__init__.py
WebSearcher/classifiers/footer.py
WebSearcher/classifiers/header_components.py
WebSearcher/classifiers/header_text.py
WebSearcher/classifiers/main.py
WebSearcher/component_parsers/__init__.py
WebSearcher/component_parsers/ads.py
WebSearcher/component_parsers/available_on.py
WebSearcher/component_parsers/banner.py
WebSearcher/component_parsers/discussions_and_forums.py
WebSearcher/component_parsers/footer.py
WebSearcher/component_parsers/general.py
WebSearcher/component_parsers/general_questions.py
WebSearcher/component_parsers/images.py
WebSearcher/component_parsers/knowledge.py
WebSearcher/component_parsers/knowledge_rhs.py
WebSearcher/component_parsers/latest_from.py
WebSearcher/component_parsers/local_news.py
WebSearcher/component_parsers/local_results.py
WebSearcher/component_parsers/map_results.py
WebSearcher/component_parsers/news_quotes.py
WebSearcher/component_parsers/notices.py
WebSearcher/component_parsers/people_also_ask.py
WebSearcher/component_parsers/perspectives.py
WebSearcher/component_parsers/recent_posts.py
WebSearcher/component_parsers/scholarly_articles.py
WebSearcher/component_parsers/searches_related.py
WebSearcher/component_parsers/shopping_ads.py
WebSearcher/component_parsers/top_image_carousel.py
WebSearcher/component_parsers/top_stories.py
WebSearcher/component_parsers/twitter_cards.py
WebSearcher/component_parsers/twitter_result.py
WebSearcher/component_parsers/videos.py
WebSearcher/component_parsers/view_more_news.py
WebSearcher/components.py
WebSearcher/extractors/__init__.py
WebSearcher/extractors/extractor_footer.py
WebSearcher/extractors/extractor_header.py
WebSearcher/extractors/extractor_main.py
WebSearcher/extractors/extractor_rhs.py
WebSearcher/locations.py
WebSearcher/logger.py
WebSearcher/models/__init__.py
WebSearcher/models/cmpt_mappings.py
WebSearcher/models/configs.py
WebSearcher/models/data.py
WebSearcher/models/searches.py
WebSearcher/parsers.py
websearcher-0.6.6.dist-info/METADATA
websearcher-0.6.6.dist-info/WHEEL
websearcher-0.6.6.dist-info/entry_points.txt
websearcher-0.6.6.dist-info/licenses/LICENSE
websearcher-0.6.6.dist-info/RECORD
