Metadata-Version: 2.4
Name: WebSearcher
Version: 0.6.6
Summary: Tools for conducting, collecting, and parsing web search
License-Expression: GPL-3.0
License-File: LICENSE
Keywords: web,search,parser
Author: Ronald E. Robertson
Author-email: <rer@acm.org>
Requires-Python: >=3.10
Classifier: Programming Language :: Python :: 3
Classifier: Programming Language :: Python :: 3.10
Classifier: Programming Language :: Python :: 3.11
Classifier: Programming Language :: Python :: 3.12
Classifier: Programming Language :: Python :: 3.13
Classifier: Programming Language :: Python :: 3.14
Requires-Dist: beautifulsoup4 (>=4.12.3)
Requires-Dist: brotli (>=1.1.0)
Requires-Dist: lxml (>=5.3.0)
Requires-Dist: orjson (>=3.10.16,<4.0.0)
Requires-Dist: pandas (>=2.2.3)
Requires-Dist: protobuf (>=6.31.1,<7.0.0)
Requires-Dist: pydantic (>=2.9.2)
Requires-Dist: requests (>=2.32.4)
Requires-Dist: selenium (>=4.9.0)
Requires-Dist: tldextract (>=5.1.2)
Requires-Dist: undetected-chromedriver (>=3.5.5)
Project-URL: Homepage, http://github.com/gitronald/WebSearcher
Project-URL: Repository, http://github.com/gitronald/WebSearcher
